adaptive_floor/__init__.py
adaptive_floor/main.py
adapter_floor-0.1.6.dist-info/LICENSE
adapter_floor-0.1.6.dist-info/METADATA
adapter_floor-0.1.6.dist-info/WHEEL
adapter_floor-0.1.6.dist-info/top_level.txt
adapter_floor-0.1.6.dist-info/RECORD
